oapi/__init__.py
oapi/_multipart_request.py
oapi/_utilities.py
oapi/client.py
oapi/errors.py
oapi/model.py
oapi/py.typed
oapi/oas/__init__.py
oapi/oas/model.py
oapi/oas/py.typed
oapi/oas/references.py
oapi-2.4.4.dist-info/METADATA
oapi-2.4.4.dist-info/WHEEL
oapi-2.4.4.dist-info/licenses/LICENSE
oapi-2.4.4.dist-info/RECORD
