Metadata-Version: 2.4
Name: oapi
Version: 2.4.4
Summary: A library for generating web API clients from OpenAPI documents
Project-URL: Documentation, https://oapi.enorganic.org
Project-URL: Repository, https://github.com/enorganic/oapi
Author-email: david@belais.me
License-Expression: MIT
License-File: LICENSE
Keywords: OpenAPI
Requires-Python: ~=3.9
Requires-Dist: jsonpointer<4.0,>2.3
Requires-Dist: sob~=2.1
Requires-Dist: typing-extensions
Provides-Extra: all
Requires-Dist: pyyaml>2; extra == 'all'
Provides-Extra: yaml
Requires-Dist: pyyaml>2; extra == 'yaml'
